setup_user/__init__.py
setup_user/setup_user.py
setup_user-1.0.0.dist-info/METADATA
setup_user-1.0.0.dist-info/WHEEL
setup_user-1.0.0.dist-info/entry_points.txt
setup_user-1.0.0.dist-info/top_level.txt
setup_user-1.0.0.dist-info/RECORD
